ibm_watsonx_data_integration/__init__.py
ibm_watsonx_data_integration/__version__.py
ibm_watsonx_data_integration/platform.py
ibm_watsonx_data_integration/codegen/README.md
ibm_watsonx_data_integration/codegen/__init__.py
ibm_watsonx_data_integration/codegen/code.py
ibm_watsonx_data_integration/codegen/generator.py
ibm_watsonx_data_integration/codegen/preamble.py
ibm_watsonx_data_integration/codegen/_templates/connection_preamble.py.jinja
ibm_watsonx_data_integration/codegen/_templates/create_connection.py.jinja
ibm_watsonx_data_integration/codegen/processors/__init__.py
ibm_watsonx_data_integration/codegen/processors/connection_processor.py
ibm_watsonx_data_integration/codegen/processors/streaming_processor/__init__.py
ibm_watsonx_data_integration/codegen/processors/streaming_processor/streaming_flow_graph.py
ibm_watsonx_data_integration/codegen/processors/streaming_processor/streaming_processor.py
ibm_watsonx_data_integration/codegen/sources/__init__.py
ibm_watsonx_data_integration/codegen/sources/base_source.py
ibm_watsonx_data_integration/codegen/sources/connection_object_source.py
ibm_watsonx_data_integration/codegen/sources/flow_object_source.py
ibm_watsonx_data_integration/common/__init__.py
ibm_watsonx_data_integration/common/auth.py
ibm_watsonx_data_integration/common/constants.py
ibm_watsonx_data_integration/common/exceptions.py
ibm_watsonx_data_integration/common/json_patch_format.py
ibm_watsonx_data_integration/common/models.py
ibm_watsonx_data_integration/common/utils.py
ibm_watsonx_data_integration/cpd_api/__init__.py
ibm_watsonx_data_integration/cpd_api/access_groups_api.py
ibm_watsonx_data_integration/cpd_api/access_groups_api_on_prem.py
ibm_watsonx_data_integration/cpd_api/account_api.py
ibm_watsonx_data_integration/cpd_api/adapters.py
ibm_watsonx_data_integration/cpd_api/base.py
ibm_watsonx_data_integration/cpd_api/broker_api.py
ibm_watsonx_data_integration/cpd_api/connections_api.py
ibm_watsonx_data_integration/cpd_api/global_catalog_api.py
ibm_watsonx_data_integration-1.0.0.dist-info/licenses/LICENSE
ibm_watsonx_data_integration-1.0.0.dist-info/METADATA
ibm_watsonx_data_integration-1.0.0.dist-info/WHEEL
ibm_watsonx_data_integration-1.0.0.dist-info/top_level.txt
ibm_watsonx_data_integration-1.0.0.dist-info/RECORD
