Metadata-Version: 2.4
Name: ibm-watsonx-data-integration
Version: 1.0.0
Summary: A Python SDK for watsonx.data integration.
Author: IBM
License-Expression: Apache-2.0
Project-URL: Documentation, https://ibm.github.io/ibm-watsonx-data-integration-sdk/
Classifier: Development Status :: 5 - Production/Stable
Classifier: Programming Language :: Python :: 3.10
Classifier: Programming Language :: Python :: 3.11
Classifier: Programming Language :: Python :: 3.12
Requires-Python: >=3.10
License-File: LICENSE
Requires-Dist: inflection~=0.5.1
Requires-Dist: requests>=2.32.3
Requires-Dist: pydantic~=2.11.7
Requires-Dist: jsondiff>=2.2.1
Requires-Dist: jinja2<4.0.0,>=3.1.6
Requires-Dist: responses>=0.25.7
Requires-Dist: ruff==0.12.9
Dynamic: license-file
